<?xml version="1.0" encoding="UTF-8"?>
<PolicyFile Name="standard" Description="输入/输出协议映射关系描述">
    <source_603>
        <Item DataSrc="WA_MFORENSICS_010100" ProtocolSrc="WA_MFORENSICS_010100" DstOut="WA_MFORENSICS_010100"/>
        <Item DataSrc="WA_MFORENSICS_010200" ProtocolSrc="WA_MFORENSICS_010200" DstOut="WA_MFORENSICS_010200"/>
        <Item DataSrc="WA_MFORENSICS_010300" ProtocolSrc="WA_MFORENSICS_010300" DstOut="WA_MFORENSICS_010300"/>
        <Item DataSrc="WA_MFORENSICS_010400" ProtocolSrc="WA_MFORENSICS_010400" DstOut="WA_MFORENSICS_010400"/>
        <Item DataSrc="WA_MFORENSICS_010500" ProtocolSrc="WA_MFORENSICS_010500" DstOut="WA_MFORENSICS_010500"/>
        <Item DataSrc="WA_MFORENSICS_010600" ProtocolSrc="WA_MFORENSICS_010600" DstOut="WA_MFORENSICS_010600"/>
        <Item DataSrc="WA_MFORENSICS_010700" ProtocolSrc="WA_MFORENSICS_010700" DstOut="WA_MFORENSICS_010700"/>
        <Item DataSrc="WA_MFORENSICS_020100" ProtocolSrc="WA_MFORENSICS_020100" DstOut="WA_MFORENSICS_020100"/>
        <Item DataSrc="WA_MFORENSICS_020200" ProtocolSrc="WA_MFORENSICS_020200" DstOut="WA_MFORENSICS_020200"/>
        <Item DataSrc="WA_MFORENSICS_020500" ProtocolSrc="WA_MFORENSICS_020500" DstOut="WA_MFORENSICS_020500"/>
        <Item DataSrc="WA_MFORENSICS_020300" ProtocolSrc="WA_MFORENSICS_020300" DstOut="WA_MFORENSICS_020300"/>
        <Item DataSrc="WA_MFORENSICS_020600" ProtocolSrc="WA_MFORENSICS_020600" DstOut="WA_MFORENSICS_020600"/>
        <Item DataSrc="WA_MFORENSICS_020400" ProtocolSrc="WA_MFORENSICS_020400" DstOut="WA_MFORENSICS_020400"/>
        <Item DataSrc="WA_MFORENSICS_020700" ProtocolSrc="WA_MFORENSICS_020700" DstOut="WA_MFORENSICS_020700"/>
        <Item DataSrc="WA_MFORENSICS_030100" ProtocolSrc="WA_MFORENSICS_030100" DstOut="WA_MFORENSICS_030100"/>
        <Item DataSrc="WA_MFORENSICS_030200" ProtocolSrc="WA_MFORENSICS_030200" DstOut="WA_MFORENSICS_030200"/>
        <Item DataSrc="WA_MFORENSICS_030300" ProtocolSrc="WA_MFORENSICS_030300" DstOut="WA_MFORENSICS_030300"/>
        <Item DataSrc="WA_MFORENSICS_040100" ProtocolSrc="WA_MFORENSICS_040100" DstOut="WA_MFORENSICS_040100"/>
        <Item DataSrc="WA_MFORENSICS_040200" ProtocolSrc="WA_MFORENSICS_040200" DstOut="WA_MFORENSICS_040200"/>
        <Item DataSrc="WA_MFORENSICS_040300" ProtocolSrc="WA_MFORENSICS_040300" DstOut="WA_MFORENSICS_040300"/>
        <Item DataSrc="WA_MFORENSICS_050200" ProtocolSrc="WA_MFORENSICS_050200" DstOut="WA_MFORENSICS_050200"/>
        <Item DataSrc="WA_MFORENSICS_050300" ProtocolSrc="WA_MFORENSICS_050300" DstOut="WA_MFORENSICS_050300"/>
        <Item DataSrc="WA_MFORENSICS_050400" ProtocolSrc="WA_MFORENSICS_050400" DstOut="WA_MFORENSICS_050400"/>
        <Item DataSrc="WA_MFORENSICS_060100" ProtocolSrc="WA_MFORENSICS_060100" DstOut="WA_MFORENSICS_060100"/>
        <Item DataSrc="WA_MFORENSICS_060200" ProtocolSrc="WA_MFORENSICS_060200" DstOut="WA_MFORENSICS_060200"/>
        <Item DataSrc="WA_MFORENSICS_060400" ProtocolSrc="WA_MFORENSICS_060400" DstOut="WA_MFORENSICS_060400"/>
        <Item DataSrc="WA_MFORENSICS_070200" ProtocolSrc="WA_MFORENSICS_070200" DstOut="WA_MFORENSICS_070200"/>
        <Item DataSrc="WA_MFORENSICS_080100" ProtocolSrc="WA_MFORENSICS_080100" DstOut="WA_MFORENSICS_080100"/>
        <Item DataSrc="WA_MFORENSICS_011000" ProtocolSrc="WA_MFORENSICS_011000" DstOut="WA_MFORENSICS_011000"/>
        <Item DataSrc="WA_MFORENSICS_060300" ProtocolSrc="WA_MFORENSICS_060300" DstOut="WA_MFORENSICS_060300"/>
        <Item DataSrc="WA_MFORENSICS_010800" ProtocolSrc="WA_MFORENSICS_010800" DstOut="WA_MFORENSICS_010800"/>
        <Item DataSrc="WA_MFORENSICS_010900" ProtocolSrc="WA_MFORENSICS_010900" DstOut="WA_MFORENSICS_010900"/>
        <Item DataSrc="WA_MFORENSICS_050100" ProtocolSrc="WA_MFORENSICS_050100" DstOut="WA_MFORENSICS_050100"/>
        <Item DataSrc="WA_MFORENSICS_020800" ProtocolSrc="WA_MFORENSICS_020800" DstOut="WA_MFORENSICS_020800"/>
        <Item DataSrc="WA_MFORENSICS_070100" ProtocolSrc="WA_MFORENSICS_070100" DstOut="WA_MFORENSICS_070100"/>
        <Item DataSrc="WA_MFORENSICS_080200" ProtocolSrc="WA_MFORENSICS_080200" DstOut="WA_MFORENSICS_080200"/>
        <Item DataSrc="WA_MFORENSICS_070500" ProtocolSrc="WA_MFORENSICS_070500" DstOut="WA_MFORENSICS_070500"/>
        <Item DataSrc="WA_MFORENSICS_030400" ProtocolSrc="WA_MFORENSICS_030400" DstOut="WA_MFORENSICS_030400"/>
        <Item DataSrc="WA_MFORENSICS_030500" ProtocolSrc="WA_MFORENSICS_030500" DstOut="WA_MFORENSICS_030500"/>
        <Item DataSrc="WA_MFORENSICS_040400" ProtocolSrc="WA_MFORENSICS_040400" DstOut="WA_MFORENSICS_040400"/>
        <Item DataSrc="WA_MFORENSICS_080300" ProtocolSrc="WA_MFORENSICS_080300" DstOut="WA_MFORENSICS_080300"/>
        <Item DataSrc="WA_MFORENSICS_040500" ProtocolSrc="WA_MFORENSICS_040500" DstOut="WA_MFORENSICS_040500"/>
        <Item DataSrc="WA_MFORENSICS_070300" ProtocolSrc="WA_MFORENSICS_070300" DstOut="WA_MFORENSICS_070300"/>
        <Item DataSrc="WA_MFORENSICS_070400" ProtocolSrc="WA_MFORENSICS_070400" DstOut="WA_MFORENSICS_070400"/>
        <Item DataSrc="WA_MFORENSICS_090100" ProtocolSrc="WA_MFORENSICS_090100" DstOut="WA_MFORENSICS_090100"/>
    </source_603>
</PolicyFile>
